{
  "track": "angular-advanced",
  "title": "Angular Advanced",
  "source": "angular.dev official docs (current, v20) + Angular University + rxjs.dev",
  "retrieved": "2026-07-19",
  "theme": "theme-angular",
  "modules": [
    { "nn": "01", "slug": "routing-fundamentals", "title": "Routing Fundamentals", "items": [
      { "id": "nga.route.setup", "label": "provideRouter, route configuration, router-outlet, routerLink, navigation", "tier": "deep", "page": null },
      { "id": "nga.route.params", "label": "Route params, query params, ActivatedRoute, programmatic navigation", "tier": "deep", "page": null }
    ]},
    { "nn": "02", "slug": "routing-advanced", "title": "Routing Advanced", "items": [
      { "id": "nga.route.lazy", "label": "Child/nested routes, lazy loading (loadComponent/loadChildren)", "tier": "deep", "page": null },
      { "id": "nga.route.guards", "label": "Functional route guards (CanActivate/CanDeactivate/CanMatch), resolvers", "tier": "deep", "page": null }
    ]},
    { "nn": "03", "slug": "rxjs-observables", "title": "RxJS: Observables and Operators", "items": [
      { "id": "nga.rx.observables", "label": "Observables, creation, marble intuition, pipeable operators (map/filter/tap)", "tier": "deep", "page": null },
      { "id": "nga.rx.flattening", "label": "Higher-order mapping (switchMap/mergeMap/concatMap/exhaustMap) and when to use each", "tier": "deep", "page": null }
    ]},
    { "nn": "04", "slug": "rxjs-subjects", "title": "RxJS: Subjects, Combination and Error Handling", "items": [
      { "id": "nga.rx.subjects", "label": "Subject/BehaviorSubject/ReplaySubject, hot vs cold, multicasting", "tier": "deep", "page": null },
      { "id": "nga.rx.combine", "label": "Combination (combineLatest/forkJoin/merge/zip), error handling (catchError/retry), subscription management", "tier": "deep", "page": null }
    ]},
    { "nn": "05", "slug": "advanced-http", "title": "Advanced HTTP", "items": [
      { "id": "nga.http.interceptors", "label": "Functional interceptors, auth/error/retry, HttpContext", "tier": "deep", "page": null },
      { "id": "nga.http.patterns", "label": "Caching, HttpParams/HttpHeaders, request cancellation, typed clients", "tier": "deep", "page": null }
    ]},
    { "nn": "06", "slug": "content-projection", "title": "Content Projection and Templates", "items": [
      { "id": "nga.tmpl.projection", "label": "ng-content, multi-slot projection, ng-container", "tier": "deep", "page": null },
      { "id": "nga.tmpl.templateref", "label": "ng-template, TemplateRef, ngTemplateOutlet, structural directive microsyntax", "tier": "deep", "page": null }
    ]},
    { "nn": "07", "slug": "dynamic-components", "title": "Dynamic Components", "items": [
      { "id": "nga.dyn.viewcontainer", "label": "ViewContainerRef, createComponent, ngComponentOutlet", "tier": "deep", "page": null },
      { "id": "nga.dyn.inputs", "label": "Passing inputs/outputs to dynamic components, cleanup", "tier": "deep", "page": null }
    ]},
    { "nn": "08", "slug": "advanced-directives", "title": "Advanced Directives", "items": [
      { "id": "nga.dir.structural", "label": "Custom structural directives, the microsyntax, TemplateRef/ViewContainerRef", "tier": "deep", "page": null },
      { "id": "nga.dir.host", "label": "Host directives (directive composition API), Renderer2, HostBinding/HostListener", "tier": "deep", "page": null }
    ]},
    { "nn": "09", "slug": "performance", "title": "Performance Optimization", "items": [
      { "id": "nga.perf.cd", "label": "OnPush deep, trackBy / @for track, pure pipes, avoiding CD work", "tier": "deep", "page": null },
      { "id": "nga.perf.defer", "label": "Deferred loading (@defer), preloading strategies, bundle/runtime optimization", "tier": "deep", "page": null }
    ]},
    { "nn": "10", "slug": "ssr-hydration", "title": "Server-Side Rendering and Hydration", "items": [
      { "id": "nga.ssr.render", "label": "Angular SSR (Universal), prerendering, the server build", "tier": "deep", "page": null },
      { "id": "nga.ssr.hydration", "label": "Hydration (full + incremental @defer hydration), SEO, TransferState", "tier": "deep", "page": null }
    ]},
    { "nn": "11", "slug": "i18n-a11y", "title": "Internationalization and Accessibility", "items": [
      { "id": "nga.i18n.translate", "label": "Angular i18n (@angular/localize), extraction, locales, runtime alternatives", "tier": "deep", "page": null },
      { "id": "nga.a11y.aria", "label": "Accessibility (ARIA, CDK a11y, focus management), semantic templates", "tier": "deep", "page": null }
    ]},
    { "nn": "12", "slug": "security", "title": "Security", "items": [
      { "id": "nga.sec.xss", "label": "XSS and Angular's contextual auto-sanitization, DomSanitizer, bypassSecurityTrust*", "tier": "deep", "page": null },
      { "id": "nga.sec.csp", "label": "Trusted Types/CSP, HttpClient XSRF protection, security best practices", "tier": "deep", "page": null }
    ]},
    { "nn": "13", "slug": "libraries-build", "title": "Libraries and the Build System", "items": [
      { "id": "nga.build.system", "label": "The application build system (esbuild/Vite), configuration, budgets", "tier": "deep", "page": null },
      { "id": "nga.build.libs", "label": "Building libraries (ng-packagr), monorepos (Nx awareness), schematics overview", "tier": "survey", "page": null }
    ]},
    { "nn": "14", "slug": "pwa-workers", "title": "PWA, Workers and Advanced Patterns", "items": [
      { "id": "nga.adv.pwa", "label": "Service workers / PWA (@angular/service-worker), app shell, caching strategies", "tier": "deep", "page": null },
      { "id": "nga.adv.workers", "label": "Web workers, micro-frontends awareness, module federation overview", "tier": "survey", "page": null }
    ]}
  ]
}
